aioproxy.py
setup.py
aioproxy.egg-info/PKG-INFO
aioproxy.egg-info/SOURCES.txt
aioproxy.egg-info/dependency_links.txt
aioproxy.egg-info/requires.txt
aioproxy.egg-info/top_level.txt