Metadata-Version: 1.0
Name: aioproxy
Version: 0.0.4
Summary: reverse proxy with aiohttp
Home-page: https://github.com/weargoggles/aioproxy
Author: Pete Wildsmith
Author-email: pete@weargoggles.co.uk
License: UNKNOWN
Platform: UNKNOWN
